MANIFEST.in
README.rst
setup.py
zhihu_crawler/__init__.py
zhihu_crawler.egg-info/PKG-INFO
zhihu_crawler.egg-info/SOURCES.txt
zhihu_crawler.egg-info/dependency_links.txt
zhihu_crawler.egg-info/top_level.txt
zhihu_crawler.egg-info/zip-safe
zhihu_crawler/common/__init__.py
zhihu_crawler/common/encrypt.js
zhihu_crawler/common/encrypt.py
zhihu_crawler/common/__pycache__/__init__.cpython-37.pyc
zhihu_crawler/common/__pycache__/encrypt.cpython-37.pyc
zhihu_crawler/common/node_modules/.bin/acorn
zhihu_crawler/common/node_modules/.bin/acorn.cmd
zhihu_crawler/common/node_modules/.bin/acorn.ps1
zhihu_crawler/common/node_modules/.bin/btoa
zhihu_crawler/common/node_modules/.bin/btoa.cmd
zhihu_crawler/common/node_modules/.bin/btoa.ps1
zhihu_crawler/common/node_modules/.bin/escodegen
zhihu_crawler/common/node_modules/.bin/escodegen.cmd
zhihu_crawler/common/node_modules/.bin/escodegen.ps1
zhihu_crawler/common/node_modules/.bin/esgenerate
zhihu_crawler/common/node_modules/.bin/esgenerate.cmd
zhihu_crawler/common/node_modules/.bin/esgenerate.ps1
zhihu_crawler/common/node_modules/.bin/esparse
zhihu_crawler/common/node_modules/.bin/esparse.cmd
zhihu_crawler/common/node_modules/.bin/esparse.ps1
zhihu_crawler/common/node_modules/.bin/esvalidate
zhihu_crawler/common/node_modules/.bin/esvalidate.cmd
zhihu_crawler/common/node_modules/.bin/esvalidate.ps1
zhihu_crawler/common/node_modules/.bin/sshpk-conv
zhihu_crawler/common/node_modules/.bin/sshpk-conv.cmd
zhihu_crawler/common/node_modules/.bin/sshpk-conv.ps1
zhihu_crawler/common/node_modules/.bin/sshpk-sign
zhihu_crawler/common/node_modules/.bin/sshpk-sign.cmd
zhihu_crawler/common/node_modules/.bin/sshpk-sign.ps1
zhihu_crawler/common/node_modules/.bin/sshpk-verify
zhihu_crawler/common/node_modules/.bin/sshpk-verify.cmd
zhihu_crawler/common/node_modules/.bin/sshpk-verify.ps1
zhihu_crawler/common/node_modules/.bin/uuid
zhihu_crawler/common/node_modules/.bin/uuid.cmd
zhihu_crawler/common/node_modules/.bin/uuid.ps1
zhihu_crawler/common/node_modules/abab/CHANGELOG.md
zhihu_crawler/common/node_modules/abab/LICENSE.md
zhihu_crawler/common/node_modules/abab/README.md
zhihu_crawler/common/node_modules/abab/index.d.ts
zhihu_crawler/common/node_modules/parse5/lib/extensions/location-info/open-element-stack-mixin.js
zhihu_crawler/common/node_modules/parse5/lib/extensions/location-info/parser-mixin.js
zhihu_crawler/common/node_modules/parse5/lib/extensions/location-info/tokenizer-mixin.js
