Metadata-Version: 2.1
Name: zhihu-crawler
Version: 0.0.1
Summary: 知乎关键词搜索、热榜、用户信息、回答、专栏文章、评论等信息的抓取程序
Home-page: https://github.com/su17873288456/zhihu_crawler
Author: szm
Author-email: s17873288456@gmail.com
License: MIT
Keywords: zhihu zhihu_crawler zhihu_scraper crawler scraper
Platform: UNKNOWN
Classifier: License :: OSI Approved :: MIT License
Classifier: Programming Language :: Python
Classifier: Intended Audience :: Developers
Classifier: Operating System :: OS Independent
